[
  {
    "description": "An ancient golem older than the world itself.  \nHe is made of pure energy and can control gravity.  \nThrowing shards at his enemies empowered with all sorts of energies.  \n",
    "HP": 0,
    "DEF": 0,
    "ATK": 0,
    "SPD": 0,
    "STAMINA": 0,
    "LVL": 0,
    "EXP": 0,
    "icon": {
      "width": 2048,
      "height": 2048,
      "filepath": "Assets/images/textures/icons/player.png",
      "ID": -2011724227,
      "isDirty": false
    },
    "name": "Aura",
    "type": "Orion.playercharacters.Aura",
    "ID": 1,
    "components": [
      {
        "type": "Burst.Engine.Source.Core.Render.SpriteRenderer",
        "properties": {
          "color": {
            "x": 1.0,
            "y": 1.0,
            "z": 1.0,
            "w": 1.0
          },
          "sprite": {
            "width": 100.0,
            "height": 100.0,
            "texCoords": [
              {
                "x": 0.3,
                "y": 1.0
              },
              {
                "x": 0.3,
                "y": 0.9
              },
              {
                "x": 0.2,
                "y": 0.9
              },
              {
                "x": 0.2,
                "y": 1.0
              }
            ],
            "resetTexCoords": [
              {
                "x": 0.3,
                "y": 1.0
              },
              {
                "x": 0.3,
                "y": 0.9
              },
              {
                "x": 0.2,
                "y": 0.9
              },
              {
                "x": 0.2,
                "y": 1.0
              }
            ],
            "filepath": "Assets/images/spritesheets/player/Aura/aura.png",
            "ID": 1945932007,
            "isDirty": false
          },
          "name": "SpriteRenderer",
          "ID": 385185606,
          "isDirty": false
        }
      },
      {
        "type": "Burst.Engine.Source.Core.Physics.Components.Transform",
        "properties": {
          "position": {
            "x": 0.0,
            "y": 0.0
          },
          "scale": {
            "x": 1.5,
            "y": 1.5
          },
          "size": {
            "x": 1.0,
            "y": 1.0
          },
          "scaledSize": {
            "x": 1.5,
            "y": 1.5
          },
          "rotation": 0.0,
          "zIndex": 0,
          "name": "Transform",
          "ID": -683109387,
          "isDirty": false
        }
      },
      {
        "type": "Burst.Engine.Source.Core.Actor.PlayerController",
        "properties": {
          "walkSpeed": 1.9,
          "jumpBoost": 1.0,
          "jumpImpulse": 3.0,
          "slowDownForce": 0.05,
          "terminalVelocity": {
            "x": 2.1,
            "y": 3.1
          },
          "isDead": false,
          "name": "PlayerController",
          "ID": -1516388368,
          "isDirty": false
        }
      },
      {
        "type": "Burst.Engine.Source.Core.Physics.Components.Rigidbody2D",
        "properties": {
          "velocity": {
            "x": 0.0,
            "y": 0.0
          },
          "angularDamping": 0.8,
          "linearDamping": 0.9,
          "mass": 0.0,
          "bodyType": "Dynamic",
          "friction": 0.1,
          "angularVelocity": 0.0,
          "gravityScale": 1.0,
          "isSensor": false,
          "fixedRotation": false,
          "continuousCollision": true,
          "name": "Rigidbody2D",
          "ID": -1192050776,
          "isDirty": false
        }
      },
      {
        "type": "Burst.Engine.Source.Game.Animation.StateMachine",
        "properties": {
          "stateTransfers": {},
          "states": [],
          "defaultStateTitle": "",
          "name": "StateMachine",
          "ID": -698501465,
          "isDirty": false
        }
      }
    ],
    "serializedActor": true,
    "adjustSizeToTexture": false,
    "pickable": true
  },
  {
    "row": 13,
    "col": 0,
    "icon": {
      "width": 2048,
      "height": 2048,
      "filepath": "Assets/images/textures/icons/block.png",
      "ID": 1847234695,
      "isDirty": false
    },
    "name": "new Block",
    "type": "Orion.blocks.Block",
    "ID": 2,
    "components": [
      {
        "type": "Burst.Engine.Source.Core.Render.SpriteRenderer",
        "properties": {
          "color": {
            "x": 1.0,
            "y": 1.0,
            "z": 1.0,
            "w": 1.0
          },
          "sprite": {
            "width": 16.0,
            "height": 16.0,
            "texCoords": [
              {
                "x": 0.15625,
                "y": 0.09375
              },
              {
                "x": 0.15625,
                "y": 0.0625
              },
              {
                "x": 0.125,
                "y": 0.0625
              },
              {
                "x": 0.125,
                "y": 0.09375
              }
            ],
            "resetTexCoords": [
              {
                "x": 0.15625,
                "y": 0.09375
              },
              {
                "x": 0.15625,
                "y": 0.0625
              },
              {
                "x": 0.125,
                "y": 0.0625
              },
              {
                "x": 0.125,
                "y": 0.09375
              }
            ],
            "filepath": "Assets/images/spritesheets/environment/tiles/blocks.png",
            "ID": 2619762,
            "isDirty": false
          },
          "name": "SpriteRenderer",
          "ID": 385185606,
          "isDirty": false
        }
      },
      {
        "type": "Burst.Engine.Source.Core.Physics.Components.Transform",
        "properties": {
          "position": {
            "x": 0.0,
            "y": -1.0
          },
          "scale": {
            "x": 1.0,
            "y": 1.0
          },
          "size": {
            "x": 1.0,
            "y": 1.0
          },
          "scaledSize": {
            "x": 1.0,
            "y": 1.0
          },
          "rotation": 0.0,
          "zIndex": 0,
          "name": "Transform",
          "ID": -683109387,
          "isDirty": false
        }
      }
    ],
    "serializedActor": true,
    "adjustSizeToTexture": false,
    "pickable": true
  },
  {
    "row": 13,
    "col": 0,
    "icon": {
      "width": 2048,
      "height": 2048,
      "filepath": "Assets/images/textures/icons/block.png",
      "ID": 1847234695,
      "isDirty": false
    },
    "name": "Block 3",
    "type": "Orion.blocks.Block",
    "ID": 3,
    "components": [
      {
        "type": "Burst.Engine.Source.Core.Render.SpriteRenderer",
        "properties": {
          "color": {
            "x": 1.0,
            "y": 1.0,
            "z": 1.0,
            "w": 1.0
          },
          "sprite": {
            "width": 16.0,
            "height": 16.0,
            "texCoords": [
              {
                "x": 0.15625,
                "y": 0.09375
              },
              {
                "x": 0.15625,
                "y": 0.0625
              },
              {
                "x": 0.125,
                "y": 0.0625
              },
              {
                "x": 0.125,
                "y": 0.09375
              }
            ],
            "resetTexCoords": [
              {
                "x": 0.15625,
                "y": 0.09375
              },
              {
                "x": 0.15625,
                "y": 0.0625
              },
              {
                "x": 0.125,
                "y": 0.0625
              },
              {
                "x": 0.125,
                "y": 0.09375
              }
            ],
            "filepath": "Assets/images/spritesheets/environment/tiles/blocks.png",
            "ID": 2619762,
            "isDirty": false
          },
          "name": "SpriteRenderer",
          "ID": 385185606,
          "isDirty": false
        }
      },
      {
        "type": "Burst.Engine.Source.Core.Physics.Components.Transform",
        "properties": {
          "position": {
            "x": 1.0,
            "y": -1.0
          },
          "scale": {
            "x": 1.0,
            "y": 1.0
          },
          "size": {
            "x": 1.0,
            "y": 1.0
          },
          "scaledSize": {
            "x": 1.0,
            "y": 1.0
          },
          "rotation": 0.0,
          "zIndex": 0,
          "name": "Transform",
          "ID": -683109387,
          "isDirty": false
        }
      }
    ],
    "serializedActor": true,
    "adjustSizeToTexture": false,
    "pickable": true
  },
  {
    "row": 13,
    "col": 0,
    "icon": {
      "width": 2048,
      "height": 2048,
      "filepath": "Assets/images/textures/icons/block.png",
      "ID": 1847234695,
      "isDirty": false
    },
    "name": "Block 4",
    "type": "Orion.blocks.Block",
    "ID": 4,
    "components": [
      {
        "type": "Burst.Engine.Source.Core.Render.SpriteRenderer",
        "properties": {
          "color": {
            "x": 1.0,
            "y": 1.0,
            "z": 1.0,
            "w": 1.0
          },
          "sprite": {
            "width": 16.0,
            "height": 16.0,
            "texCoords": [
              {
                "x": 0.15625,
                "y": 0.09375
              },
              {
                "x": 0.15625,
                "y": 0.0625
              },
              {
                "x": 0.125,
                "y": 0.0625
              },
              {
                "x": 0.125,
                "y": 0.09375
              }
            ],
            "resetTexCoords": [
              {
                "x": 0.15625,
                "y": 0.09375
              },
              {
                "x": 0.15625,
                "y": 0.0625
              },
              {
                "x": 0.125,
                "y": 0.0625
              },
              {
                "x": 0.125,
                "y": 0.09375
              }
            ],
            "filepath": "Assets/images/spritesheets/environment/tiles/blocks.png",
            "ID": 2619762,
            "isDirty": false
          },
          "name": "SpriteRenderer",
          "ID": 385185606,
          "isDirty": false
        }
      },
      {
        "type": "Burst.Engine.Source.Core.Physics.Components.Transform",
        "properties": {
          "position": {
            "x": 2.0,
            "y": -1.0
          },
          "scale": {
            "x": 1.0,
            "y": 1.0
          },
          "size": {
            "x": 1.0,
            "y": 1.0
          },
          "scaledSize": {
            "x": 1.0,
            "y": 1.0
          },
          "rotation": 0.0,
          "zIndex": 0,
          "name": "Transform",
          "ID": -683109387,
          "isDirty": false
        }
      }
    ],
    "serializedActor": true,
    "adjustSizeToTexture": false,
    "pickable": true
  },
  {
    "row": 13,
    "col": 0,
    "icon": {
      "width": 2048,
      "height": 2048,
      "filepath": "Assets/images/textures/icons/block.png",
      "ID": 1847234695,
      "isDirty": false
    },
    "name": "Block 5",
    "type": "Orion.blocks.Block",
    "ID": 5,
    "components": [
      {
        "type": "Burst.Engine.Source.Core.Render.SpriteRenderer",
        "properties": {
          "color": {
            "x": 1.0,
            "y": 1.0,
            "z": 1.0,
            "w": 1.0
          },
          "sprite": {
            "width": 16.0,
            "height": 16.0,
            "texCoords": [
              {
                "x": 0.15625,
                "y": 0.09375
              },
              {
                "x": 0.15625,
                "y": 0.0625
              },
              {
                "x": 0.125,
                "y": 0.0625
              },
              {
                "x": 0.125,
                "y": 0.09375
              }
            ],
            "resetTexCoords": [
              {
                "x": 0.15625,
                "y": 0.09375
              },
              {
                "x": 0.15625,
                "y": 0.0625
              },
              {
                "x": 0.125,
                "y": 0.0625
              },
              {
                "x": 0.125,
                "y": 0.09375
              }
            ],
            "filepath": "Assets/images/spritesheets/environment/tiles/blocks.png",
            "ID": 2619762,
            "isDirty": false
          },
          "name": "SpriteRenderer",
          "ID": 385185606,
          "isDirty": false
        }
      },
      {
        "type": "Burst.Engine.Source.Core.Physics.Components.Transform",
        "properties": {
          "position": {
            "x": 3.0,
            "y": -1.0
          },
          "scale": {
            "x": 1.0,
            "y": 1.0
          },
          "size": {
            "x": 1.0,
            "y": 1.0
          },
          "scaledSize": {
            "x": 1.0,
            "y": 1.0
          },
          "rotation": 0.0,
          "zIndex": 0,
          "name": "Transform",
          "ID": -683109387,
          "isDirty": false
        }
      }
    ],
    "serializedActor": true,
    "adjustSizeToTexture": false,
    "pickable": true
  },
  {
    "row": 13,
    "col": 0,
    "icon": {
      "width": 2048,
      "height": 2048,
      "filepath": "Assets/images/textures/icons/block.png",
      "ID": 1847234695,
      "isDirty": false
    },
    "name": "Block 6",
    "type": "Orion.blocks.Block",
    "ID": 6,
    "components": [
      {
        "type": "Burst.Engine.Source.Core.Render.SpriteRenderer",
        "properties": {
          "color": {
            "x": 1.0,
            "y": 1.0,
            "z": 1.0,
            "w": 1.0
          },
          "sprite": {
            "width": 16.0,
            "height": 16.0,
            "texCoords": [
              {
                "x": 0.15625,
                "y": 0.09375
              },
              {
                "x": 0.15625,
                "y": 0.0625
              },
              {
                "x": 0.125,
                "y": 0.0625
              },
              {
                "x": 0.125,
                "y": 0.09375
              }
            ],
            "resetTexCoords": [
              {
                "x": 0.15625,
                "y": 0.09375
              },
              {
                "x": 0.15625,
                "y": 0.0625
              },
              {
                "x": 0.125,
                "y": 0.0625
              },
              {
                "x": 0.125,
                "y": 0.09375
              }
            ],
            "filepath": "Assets/images/spritesheets/environment/tiles/blocks.png",
            "ID": 2619762,
            "isDirty": false
          },
          "name": "SpriteRenderer",
          "ID": 385185606,
          "isDirty": false
        }
      },
      {
        "type": "Burst.Engine.Source.Core.Physics.Components.Transform",
        "properties": {
          "position": {
            "x": 4.0,
            "y": -1.0
          },
          "scale": {
            "x": 1.0,
            "y": 1.0
          },
          "size": {
            "x": 1.0,
            "y": 1.0
          },
          "scaledSize": {
            "x": 1.0,
            "y": 1.0
          },
          "rotation": 0.0,
          "zIndex": 0,
          "name": "Transform",
          "ID": -683109387,
          "isDirty": false
        }
      }
    ],
    "serializedActor": true,
    "adjustSizeToTexture": false,
    "pickable": true
  },
  {
    "row": 13,
    "col": 0,
    "icon": {
      "width": 2048,
      "height": 2048,
      "filepath": "Assets/images/textures/icons/block.png",
      "ID": 1847234695,
      "isDirty": false
    },
    "name": "Block 7",
    "type": "Orion.blocks.Block",
    "ID": 7,
    "components": [
      {
        "type": "Burst.Engine.Source.Core.Render.SpriteRenderer",
        "properties": {
          "color": {
            "x": 1.0,
            "y": 1.0,
            "z": 1.0,
            "w": 1.0
          },
          "sprite": {
            "width": 16.0,
            "height": 16.0,
            "texCoords": [
              {
                "x": 0.15625,
                "y": 0.09375
              },
              {
                "x": 0.15625,
                "y": 0.0625
              },
              {
                "x": 0.125,
                "y": 0.0625
              },
              {
                "x": 0.125,
                "y": 0.09375
              }
            ],
            "resetTexCoords": [
              {
                "x": 0.15625,
                "y": 0.09375
              },
              {
                "x": 0.15625,
                "y": 0.0625
              },
              {
                "x": 0.125,
                "y": 0.0625
              },
              {
                "x": 0.125,
                "y": 0.09375
              }
            ],
            "filepath": "Assets/images/spritesheets/environment/tiles/blocks.png",
            "ID": 2619762,
            "isDirty": false
          },
          "name": "SpriteRenderer",
          "ID": 385185606,
          "isDirty": false
        }
      },
      {
        "type": "Burst.Engine.Source.Core.Physics.Components.Transform",
        "properties": {
          "position": {
            "x": 5.0,
            "y": -1.0
          },
          "scale": {
            "x": 1.0,
            "y": 1.0
          },
          "size": {
            "x": 1.0,
            "y": 1.0
          },
          "scaledSize": {
            "x": 1.0,
            "y": 1.0
          },
          "rotation": 0.0,
          "zIndex": 0,
          "name": "Transform",
          "ID": -683109387,
          "isDirty": false
        }
      }
    ],
    "serializedActor": true,
    "adjustSizeToTexture": false,
    "pickable": true
  },
  {
    "row": 13,
    "col": 0,
    "icon": {
      "width": 2048,
      "height": 2048,
      "filepath": "Assets/images/textures/icons/block.png",
      "ID": 1847234695,
      "isDirty": false
    },
    "name": "Block 8",
    "type": "Orion.blocks.Block",
    "ID": 8,
    "components": [
      {
        "type": "Burst.Engine.Source.Core.Render.SpriteRenderer",
        "properties": {
          "color": {
            "x": 1.0,
            "y": 1.0,
            "z": 1.0,
            "w": 1.0
          },
          "sprite": {
            "width": 16.0,
            "height": 16.0,
            "texCoords": [
              {
                "x": 0.15625,
                "y": 0.09375
              },
              {
                "x": 0.15625,
                "y": 0.0625
              },
              {
                "x": 0.125,
                "y": 0.0625
              },
              {
                "x": 0.125,
                "y": 0.09375
              }
            ],
            "resetTexCoords": [
              {
                "x": 0.15625,
                "y": 0.09375
              },
              {
                "x": 0.15625,
                "y": 0.0625
              },
              {
                "x": 0.125,
                "y": 0.0625
              },
              {
                "x": 0.125,
                "y": 0.09375
              }
            ],
            "filepath": "Assets/images/spritesheets/environment/tiles/blocks.png",
            "ID": 2619762,
            "isDirty": false
          },
          "name": "SpriteRenderer",
          "ID": 385185606,
          "isDirty": false
        }
      },
      {
        "type": "Burst.Engine.Source.Core.Physics.Components.Transform",
        "properties": {
          "position": {
            "x": 6.0,
            "y": -1.0
          },
          "scale": {
            "x": 1.0,
            "y": 1.0
          },
          "size": {
            "x": 1.0,
            "y": 1.0
          },
          "scaledSize": {
            "x": 1.0,
            "y": 1.0
          },
          "rotation": 0.0,
          "zIndex": 0,
          "name": "Transform",
          "ID": -683109387,
          "isDirty": false
        }
      }
    ],
    "serializedActor": true,
    "adjustSizeToTexture": false,
    "pickable": true
  },
  {
    "row": 13,
    "col": 0,
    "icon": {
      "width": 2048,
      "height": 2048,
      "filepath": "Assets/images/textures/icons/block.png",
      "ID": 1847234695,
      "isDirty": false
    },
    "name": "Block 9",
    "type": "Orion.blocks.Block",
    "ID": 9,
    "components": [
      {
        "type": "Burst.Engine.Source.Core.Render.SpriteRenderer",
        "properties": {
          "color": {
            "x": 1.0,
            "y": 1.0,
            "z": 1.0,
            "w": 1.0
          },
          "sprite": {
            "width": 16.0,
            "height": 16.0,
            "texCoords": [
              {
                "x": 0.15625,
                "y": 0.09375
              },
              {
                "x": 0.15625,
                "y": 0.0625
              },
              {
                "x": 0.125,
                "y": 0.0625
              },
              {
                "x": 0.125,
                "y": 0.09375
              }
            ],
            "resetTexCoords": [
              {
                "x": 0.15625,
                "y": 0.09375
              },
              {
                "x": 0.15625,
                "y": 0.0625
              },
              {
                "x": 0.125,
                "y": 0.0625
              },
              {
                "x": 0.125,
                "y": 0.09375
              }
            ],
            "filepath": "Assets/images/spritesheets/environment/tiles/blocks.png",
            "ID": 2619762,
            "isDirty": false
          },
          "name": "SpriteRenderer",
          "ID": 385185606,
          "isDirty": false
        }
      },
      {
        "type": "Burst.Engine.Source.Core.Physics.Components.Transform",
        "properties": {
          "position": {
            "x": 7.0,
            "y": -1.0
          },
          "scale": {
            "x": 1.0,
            "y": 1.0
          },
          "size": {
            "x": 1.0,
            "y": 1.0
          },
          "scaledSize": {
            "x": 1.0,
            "y": 1.0
          },
          "rotation": 0.0,
          "zIndex": 0,
          "name": "Transform",
          "ID": -683109387,
          "isDirty": false
        }
      }
    ],
    "serializedActor": true,
    "adjustSizeToTexture": false,
    "pickable": true
  },
  {
    "row": 13,
    "col": 0,
    "icon": {
      "width": 2048,
      "height": 2048,
      "filepath": "Assets/images/textures/icons/block.png",
      "ID": 1847234695,
      "isDirty": false
    },
    "name": "Block 10",
    "type": "Orion.blocks.Block",
    "ID": 10,
    "components": [
      {
        "type": "Burst.Engine.Source.Core.Render.SpriteRenderer",
        "properties": {
          "color": {
            "x": 1.0,
            "y": 1.0,
            "z": 1.0,
            "w": 1.0
          },
          "sprite": {
            "width": 16.0,
            "height": 16.0,
            "texCoords": [
              {
                "x": 0.15625,
                "y": 0.09375
              },
              {
                "x": 0.15625,
                "y": 0.0625
              },
              {
                "x": 0.125,
                "y": 0.0625
              },
              {
                "x": 0.125,
                "y": 0.09375
              }
            ],
            "resetTexCoords": [
              {
                "x": 0.15625,
                "y": 0.09375
              },
              {
                "x": 0.15625,
                "y": 0.0625
              },
              {
                "x": 0.125,
                "y": 0.0625
              },
              {
                "x": 0.125,
                "y": 0.09375
              }
            ],
            "filepath": "Assets/images/spritesheets/environment/tiles/blocks.png",
            "ID": 2619762,
            "isDirty": false
          },
          "name": "SpriteRenderer",
          "ID": 385185606,
          "isDirty": false
        }
      },
      {
        "type": "Burst.Engine.Source.Core.Physics.Components.Transform",
        "properties": {
          "position": {
            "x": 8.0,
            "y": -1.0
          },
          "scale": {
            "x": 1.0,
            "y": 1.0
          },
          "size": {
            "x": 1.0,
            "y": 1.0
          },
          "scaledSize": {
            "x": 1.0,
            "y": 1.0
          },
          "rotation": 0.0,
          "zIndex": 0,
          "name": "Transform",
          "ID": -683109387,
          "isDirty": false
        }
      }
    ],
    "serializedActor": true,
    "adjustSizeToTexture": false,
    "pickable": true
  },
  {
    "row": 13,
    "col": 0,
    "icon": {
      "width": 2048,
      "height": 2048,
      "filepath": "Assets/images/textures/icons/block.png",
      "ID": 1847234695,
      "isDirty": false
    },
    "name": "Block 11",
    "type": "Orion.blocks.Block",
    "ID": 11,
    "components": [
      {
        "type": "Burst.Engine.Source.Core.Render.SpriteRenderer",
        "properties": {
          "color": {
            "x": 1.0,
            "y": 1.0,
            "z": 1.0,
            "w": 1.0
          },
          "sprite": {
            "width": 16.0,
            "height": 16.0,
            "texCoords": [
              {
                "x": 0.15625,
                "y": 0.09375
              },
              {
                "x": 0.15625,
                "y": 0.0625
              },
              {
                "x": 0.125,
                "y": 0.0625
              },
              {
                "x": 0.125,
                "y": 0.09375
              }
            ],
            "resetTexCoords": [
              {
                "x": 0.15625,
                "y": 0.09375
              },
              {
                "x": 0.15625,
                "y": 0.0625
              },
              {
                "x": 0.125,
                "y": 0.0625
              },
              {
                "x": 0.125,
                "y": 0.09375
              }
            ],
            "filepath": "Assets/images/spritesheets/environment/tiles/blocks.png",
            "ID": 2619762,
            "isDirty": false
          },
          "name": "SpriteRenderer",
          "ID": 385185606,
          "isDirty": false
        }
      },
      {
        "type": "Burst.Engine.Source.Core.Physics.Components.Transform",
        "properties": {
          "position": {
            "x": 9.0,
            "y": -1.0
          },
          "scale": {
            "x": 1.0,
            "y": 1.0
          },
          "size": {
            "x": 1.0,
            "y": 1.0
          },
          "scaledSize": {
            "x": 1.0,
            "y": 1.0
          },
          "rotation": 0.0,
          "zIndex": 0,
          "name": "Transform",
          "ID": -683109387,
          "isDirty": false
        }
      }
    ],
    "serializedActor": true,
    "adjustSizeToTexture": false,
    "pickable": true
  },
  {
    "row": 13,
    "col": 0,
    "icon": {
      "width": 2048,
      "height": 2048,
      "filepath": "Assets/images/textures/icons/block.png",
      "ID": 1847234695,
      "isDirty": false
    },
    "name": "Block 12",
    "type": "Orion.blocks.Block",
    "ID": 12,
    "components": [
      {
        "type": "Burst.Engine.Source.Core.Render.SpriteRenderer",
        "properties": {
          "color": {
            "x": 1.0,
            "y": 1.0,
            "z": 1.0,
            "w": 1.0
          },
          "sprite": {
            "width": 16.0,
            "height": 16.0,
            "texCoords": [
              {
                "x": 0.15625,
                "y": 0.09375
              },
              {
                "x": 0.15625,
                "y": 0.0625
              },
              {
                "x": 0.125,
                "y": 0.0625
              },
              {
                "x": 0.125,
                "y": 0.09375
              }
            ],
            "resetTexCoords": [
              {
                "x": 0.15625,
                "y": 0.09375
              },
              {
                "x": 0.15625,
                "y": 0.0625
              },
              {
                "x": 0.125,
                "y": 0.0625
              },
              {
                "x": 0.125,
                "y": 0.09375
              }
            ],
            "filepath": "Assets/images/spritesheets/environment/tiles/blocks.png",
            "ID": 2619762,
            "isDirty": false
          },
          "name": "SpriteRenderer",
          "ID": 385185606,
          "isDirty": false
        }
      },
      {
        "type": "Burst.Engine.Source.Core.Physics.Components.Transform",
        "properties": {
          "position": {
            "x": 10.0,
            "y": -1.0
          },
          "scale": {
            "x": 1.0,
            "y": 1.0
          },
          "size": {
            "x": 1.0,
            "y": 1.0
          },
          "scaledSize": {
            "x": 1.0,
            "y": 1.0
          },
          "rotation": 0.0,
          "zIndex": 0,
          "name": "Transform",
          "ID": -683109387,
          "isDirty": false
        }
      }
    ],
    "serializedActor": true,
    "adjustSizeToTexture": false,
    "pickable": true
  },
  {
    "row": 13,
    "col": 0,
    "icon": {
      "width": 2048,
      "height": 2048,
      "filepath": "Assets/images/textures/icons/block.png",
      "ID": 1847234695,
      "isDirty": false
    },
    "name": "Block 13",
    "type": "Orion.blocks.Block",
    "ID": 13,
    "components": [
      {
        "type": "Burst.Engine.Source.Core.Render.SpriteRenderer",
        "properties": {
          "color": {
            "x": 1.0,
            "y": 1.0,
            "z": 1.0,
            "w": 1.0
          },
          "sprite": {
            "width": 16.0,
            "height": 16.0,
            "texCoords": [
              {
                "x": 0.15625,
                "y": 0.09375
              },
              {
                "x": 0.15625,
                "y": 0.0625
              },
              {
                "x": 0.125,
                "y": 0.0625
              },
              {
                "x": 0.125,
                "y": 0.09375
              }
            ],
            "resetTexCoords": [
              {
                "x": 0.15625,
                "y": 0.09375
              },
              {
                "x": 0.15625,
                "y": 0.0625
              },
              {
                "x": 0.125,
                "y": 0.0625
              },
              {
                "x": 0.125,
                "y": 0.09375
              }
            ],
            "filepath": "Assets/images/spritesheets/environment/tiles/blocks.png",
            "ID": 2619762,
            "isDirty": false
          },
          "name": "SpriteRenderer",
          "ID": 385185606,
          "isDirty": false
        }
      },
      {
        "type": "Burst.Engine.Source.Core.Physics.Components.Transform",
        "properties": {
          "position": {
            "x": 11.0,
            "y": -1.0
          },
          "scale": {
            "x": 1.0,
            "y": 1.0
          },
          "size": {
            "x": 1.0,
            "y": 1.0
          },
          "scaledSize": {
            "x": 1.0,
            "y": 1.0
          },
          "rotation": 0.0,
          "zIndex": 0,
          "name": "Transform",
          "ID": -683109387,
          "isDirty": false
        }
      }
    ],
    "serializedActor": true,
    "adjustSizeToTexture": false,
    "pickable": true
  },
  {
    "row": 13,
    "col": 0,
    "icon": {
      "width": 2048,
      "height": 2048,
      "filepath": "Assets/images/textures/icons/block.png",
      "ID": 1847234695,
      "isDirty": false
    },
    "name": "Block 14",
    "type": "Orion.blocks.Block",
    "ID": 14,
    "components": [
      {
        "type": "Burst.Engine.Source.Core.Render.SpriteRenderer",
        "properties": {
          "color": {
            "x": 1.0,
            "y": 1.0,
            "z": 1.0,
            "w": 1.0
          },
          "sprite": {
            "width": 16.0,
            "height": 16.0,
            "texCoords": [
              {
                "x": 0.15625,
                "y": 0.09375
              },
              {
                "x": 0.15625,
                "y": 0.0625
              },
              {
                "x": 0.125,
                "y": 0.0625
              },
              {
                "x": 0.125,
                "y": 0.09375
              }
            ],
            "resetTexCoords": [
              {
                "x": 0.15625,
                "y": 0.09375
              },
              {
                "x": 0.15625,
                "y": 0.0625
              },
              {
                "x": 0.125,
                "y": 0.0625
              },
              {
                "x": 0.125,
                "y": 0.09375
              }
            ],
            "filepath": "Assets/images/spritesheets/environment/tiles/blocks.png",
            "ID": 2619762,
            "isDirty": false
          },
          "name": "SpriteRenderer",
          "ID": 385185606,
          "isDirty": false
        }
      },
      {
        "type": "Burst.Engine.Source.Core.Physics.Components.Transform",
        "properties": {
          "position": {
            "x": -12.0,
            "y": -1.0
          },
          "scale": {
            "x": 1.0,
            "y": 1.0
          },
          "size": {
            "x": 1.0,
            "y": 1.0
          },
          "scaledSize": {
            "x": 1.0,
            "y": 1.0
          },
          "rotation": 0.0,
          "zIndex": 0,
          "name": "Transform",
          "ID": -683109387,
          "isDirty": false
        }
      }
    ],
    "serializedActor": true,
    "adjustSizeToTexture": false,
    "pickable": true
  },
  {
    "row": 13,
    "col": 0,
    "icon": {
      "width": 2048,
      "height": 2048,
      "filepath": "Assets/images/textures/icons/block.png",
      "ID": 1847234695,
      "isDirty": false
    },
    "name": "Block 15",
    "type": "Orion.blocks.Block",
    "ID": 15,
    "components": [
      {
        "type": "Burst.Engine.Source.Core.Render.SpriteRenderer",
        "properties": {
          "color": {
            "x": 1.0,
            "y": 1.0,
            "z": 1.0,
            "w": 1.0
          },
          "sprite": {
            "width": 16.0,
            "height": 16.0,
            "texCoords": [
              {
                "x": 0.15625,
                "y": 0.09375
              },
              {
                "x": 0.15625,
                "y": 0.0625
              },
              {
                "x": 0.125,
                "y": 0.0625
              },
              {
                "x": 0.125,
                "y": 0.09375
              }
            ],
            "resetTexCoords": [
              {
                "x": 0.15625,
                "y": 0.09375
              },
              {
                "x": 0.15625,
                "y": 0.0625
              },
              {
                "x": 0.125,
                "y": 0.0625
              },
              {
                "x": 0.125,
                "y": 0.09375
              }
            ],
            "filepath": "Assets/images/spritesheets/environment/tiles/blocks.png",
            "ID": 2619762,
            "isDirty": false
          },
          "name": "SpriteRenderer",
          "ID": 385185606,
          "isDirty": false
        }
      },
      {
        "type": "Burst.Engine.Source.Core.Physics.Components.Transform",
        "properties": {
          "position": {
            "x": -11.0,
            "y": -1.0
          },
          "scale": {
            "x": 1.0,
            "y": 1.0
          },
          "size": {
            "x": 1.0,
            "y": 1.0
          },
          "scaledSize": {
            "x": 1.0,
            "y": 1.0
          },
          "rotation": 0.0,
          "zIndex": 0,
          "name": "Transform",
          "ID": -683109387,
          "isDirty": false
        }
      }
    ],
    "serializedActor": true,
    "adjustSizeToTexture": false,
    "pickable": true
  },
  {
    "row": 13,
    "col": 0,
    "icon": {
      "width": 2048,
      "height": 2048,
      "filepath": "Assets/images/textures/icons/block.png",
      "ID": 1847234695,
      "isDirty": false
    },
    "name": "Block 16",
    "type": "Orion.blocks.Block",
    "ID": 16,
    "components": [
      {
        "type": "Burst.Engine.Source.Core.Render.SpriteRenderer",
        "properties": {
          "color": {
            "x": 1.0,
            "y": 1.0,
            "z": 1.0,
            "w": 1.0
          },
          "sprite": {
            "width": 16.0,
            "height": 16.0,
            "texCoords": [
              {
                "x": 0.15625,
                "y": 0.09375
              },
              {
                "x": 0.15625,
                "y": 0.0625
              },
              {
                "x": 0.125,
                "y": 0.0625
              },
              {
                "x": 0.125,
                "y": 0.09375
              }
            ],
            "resetTexCoords": [
              {
                "x": 0.15625,
                "y": 0.09375
              },
              {
                "x": 0.15625,
                "y": 0.0625
              },
              {
                "x": 0.125,
                "y": 0.0625
              },
              {
                "x": 0.125,
                "y": 0.09375
              }
            ],
            "filepath": "Assets/images/spritesheets/environment/tiles/blocks.png",
            "ID": 2619762,
            "isDirty": false
          },
          "name": "SpriteRenderer",
          "ID": 385185606,
          "isDirty": false
        }
      },
      {
        "type": "Burst.Engine.Source.Core.Physics.Components.Transform",
        "properties": {
          "position": {
            "x": -10.0,
            "y": -1.0
          },
          "scale": {
            "x": 1.0,
            "y": 1.0
          },
          "size": {
            "x": 1.0,
            "y": 1.0
          },
          "scaledSize": {
            "x": 1.0,
            "y": 1.0
          },
          "rotation": 0.0,
          "zIndex": 0,
          "name": "Transform",
          "ID": -683109387,
          "isDirty": false
        }
      }
    ],
    "serializedActor": true,
    "adjustSizeToTexture": false,
    "pickable": true
  },
  {
    "row": 13,
    "col": 0,
    "icon": {
      "width": 2048,
      "height": 2048,
      "filepath": "Assets/images/textures/icons/block.png",
      "ID": 1847234695,
      "isDirty": false
    },
    "name": "Block 17",
    "type": "Orion.blocks.Block",
    "ID": 17,
    "components": [
      {
        "type": "Burst.Engine.Source.Core.Render.SpriteRenderer",
        "properties": {
          "color": {
            "x": 1.0,
            "y": 1.0,
            "z": 1.0,
            "w": 1.0
          },
          "sprite": {
            "width": 16.0,
            "height": 16.0,
            "texCoords": [
              {
                "x": 0.15625,
                "y": 0.09375
              },
              {
                "x": 0.15625,
                "y": 0.0625
              },
              {
                "x": 0.125,
                "y": 0.0625
              },
              {
                "x": 0.125,
                "y": 0.09375
              }
            ],
            "resetTexCoords": [
              {
                "x": 0.15625,
                "y": 0.09375
              },
              {
                "x": 0.15625,
                "y": 0.0625
              },
              {
                "x": 0.125,
                "y": 0.0625
              },
              {
                "x": 0.125,
                "y": 0.09375
              }
            ],
            "filepath": "Assets/images/spritesheets/environment/tiles/blocks.png",
            "ID": 2619762,
            "isDirty": false
          },
          "name": "SpriteRenderer",
          "ID": 385185606,
          "isDirty": false
        }
      },
      {
        "type": "Burst.Engine.Source.Core.Physics.Components.Transform",
        "properties": {
          "position": {
            "x": -9.0,
            "y": -1.0
          },
          "scale": {
            "x": 1.0,
            "y": 1.0
          },
          "size": {
            "x": 1.0,
            "y": 1.0
          },
          "scaledSize": {
            "x": 1.0,
            "y": 1.0
          },
          "rotation": 0.0,
          "zIndex": 0,
          "name": "Transform",
          "ID": -683109387,
          "isDirty": false
        }
      }
    ],
    "serializedActor": true,
    "adjustSizeToTexture": false,
    "pickable": true
  },
  {
    "row": 13,
    "col": 0,
    "icon": {
      "width": 2048,
      "height": 2048,
      "filepath": "Assets/images/textures/icons/block.png",
      "ID": 1847234695,
      "isDirty": false
    },
    "name": "Block 18",
    "type": "Orion.blocks.Block",
    "ID": 18,
    "components": [
      {
        "type": "Burst.Engine.Source.Core.Render.SpriteRenderer",
        "properties": {
          "color": {
            "x": 1.0,
            "y": 1.0,
            "z": 1.0,
            "w": 1.0
          },
          "sprite": {
            "width": 16.0,
            "height": 16.0,
            "texCoords": [
              {
                "x": 0.15625,
                "y": 0.09375
              },
              {
                "x": 0.15625,
                "y": 0.0625
              },
              {
                "x": 0.125,
                "y": 0.0625
              },
              {
                "x": 0.125,
                "y": 0.09375
              }
            ],
            "resetTexCoords": [
              {
                "x": 0.15625,
                "y": 0.09375
              },
              {
                "x": 0.15625,
                "y": 0.0625
              },
              {
                "x": 0.125,
                "y": 0.0625
              },
              {
                "x": 0.125,
                "y": 0.09375
              }
            ],
            "filepath": "Assets/images/spritesheets/environment/tiles/blocks.png",
            "ID": 2619762,
            "isDirty": false
          },
          "name": "SpriteRenderer",
          "ID": 385185606,
          "isDirty": false
        }
      },
      {
        "type": "Burst.Engine.Source.Core.Physics.Components.Transform",
        "properties": {
          "position": {
            "x": -8.0,
            "y": -1.0
          },
          "scale": {
            "x": 1.0,
            "y": 1.0
          },
          "size": {
            "x": 1.0,
            "y": 1.0
          },
          "scaledSize": {
            "x": 1.0,
            "y": 1.0
          },
          "rotation": 0.0,
          "zIndex": 0,
          "name": "Transform",
          "ID": -683109387,
          "isDirty": false
        }
      }
    ],
    "serializedActor": true,
    "adjustSizeToTexture": false,
    "pickable": true
  },
  {
    "row": 13,
    "col": 0,
    "icon": {
      "width": 2048,
      "height": 2048,
      "filepath": "Assets/images/textures/icons/block.png",
      "ID": 1847234695,
      "isDirty": false
    },
    "name": "Block 19",
    "type": "Orion.blocks.Block",
    "ID": 19,
    "components": [
      {
        "type": "Burst.Engine.Source.Core.Render.SpriteRenderer",
        "properties": {
          "color": {
            "x": 1.0,
            "y": 1.0,
            "z": 1.0,
            "w": 1.0
          },
          "sprite": {
            "width": 16.0,
            "height": 16.0,
            "texCoords": [
              {
                "x": 0.15625,
                "y": 0.09375
              },
              {
                "x": 0.15625,
                "y": 0.0625
              },
              {
                "x": 0.125,
                "y": 0.0625
              },
              {
                "x": 0.125,
                "y": 0.09375
              }
            ],
            "resetTexCoords": [
              {
                "x": 0.15625,
                "y": 0.09375
              },
              {
                "x": 0.15625,
                "y": 0.0625
              },
              {
                "x": 0.125,
                "y": 0.0625
              },
              {
                "x": 0.125,
                "y": 0.09375
              }
            ],
            "filepath": "Assets/images/spritesheets/environment/tiles/blocks.png",
            "ID": 2619762,
            "isDirty": false
          },
          "name": "SpriteRenderer",
          "ID": 385185606,
          "isDirty": false
        }
      },
      {
        "type": "Burst.Engine.Source.Core.Physics.Components.Transform",
        "properties": {
          "position": {
            "x": -7.0,
            "y": -1.0
          },
          "scale": {
            "x": 1.0,
            "y": 1.0
          },
          "size": {
            "x": 1.0,
            "y": 1.0
          },
          "scaledSize": {
            "x": 1.0,
            "y": 1.0
          },
          "rotation": 0.0,
          "zIndex": 0,
          "name": "Transform",
          "ID": -683109387,
          "isDirty": false
        }
      }
    ],
    "serializedActor": true,
    "adjustSizeToTexture": false,
    "pickable": true
  },
  {
    "row": 13,
    "col": 0,
    "icon": {
      "width": 2048,
      "height": 2048,
      "filepath": "Assets/images/textures/icons/block.png",
      "ID": 1847234695,
      "isDirty": false
    },
    "name": "Block 20",
    "type": "Orion.blocks.Block",
    "ID": 20,
    "components": [
      {
        "type": "Burst.Engine.Source.Core.Render.SpriteRenderer",
        "properties": {
          "color": {
            "x": 1.0,
            "y": 1.0,
            "z": 1.0,
            "w": 1.0
          },
          "sprite": {
            "width": 16.0,
            "height": 16.0,
            "texCoords": [
              {
                "x": 0.15625,
                "y": 0.09375
              },
              {
                "x": 0.15625,
                "y": 0.0625
              },
              {
                "x": 0.125,
                "y": 0.0625
              },
              {
                "x": 0.125,
                "y": 0.09375
              }
            ],
            "resetTexCoords": [
              {
                "x": 0.15625,
                "y": 0.09375
              },
              {
                "x": 0.15625,
                "y": 0.0625
              },
              {
                "x": 0.125,
                "y": 0.0625
              },
              {
                "x": 0.125,
                "y": 0.09375
              }
            ],
            "filepath": "Assets/images/spritesheets/environment/tiles/blocks.png",
            "ID": 2619762,
            "isDirty": false
          },
          "name": "SpriteRenderer",
          "ID": 385185606,
          "isDirty": false
        }
      },
      {
        "type": "Burst.Engine.Source.Core.Physics.Components.Transform",
        "properties": {
          "position": {
            "x": -6.0,
            "y": -1.0
          },
          "scale": {
            "x": 1.0,
            "y": 1.0
          },
          "size": {
            "x": 1.0,
            "y": 1.0
          },
          "scaledSize": {
            "x": 1.0,
            "y": 1.0
          },
          "rotation": 0.0,
          "zIndex": 0,
          "name": "Transform",
          "ID": -683109387,
          "isDirty": false
        }
      }
    ],
    "serializedActor": true,
    "adjustSizeToTexture": false,
    "pickable": true
  },
  {
    "row": 13,
    "col": 0,
    "icon": {
      "width": 2048,
      "height": 2048,
      "filepath": "Assets/images/textures/icons/block.png",
      "ID": 1847234695,
      "isDirty": false
    },
    "name": "Block 21",
    "type": "Orion.blocks.Block",
    "ID": 21,
    "components": [
      {
        "type": "Burst.Engine.Source.Core.Render.SpriteRenderer",
        "properties": {
          "color": {
            "x": 1.0,
            "y": 1.0,
            "z": 1.0,
            "w": 1.0
          },
          "sprite": {
            "width": 16.0,
            "height": 16.0,
            "texCoords": [
              {
                "x": 0.15625,
                "y": 0.09375
              },
              {
                "x": 0.15625,
                "y": 0.0625
              },
              {
                "x": 0.125,
                "y": 0.0625
              },
              {
                "x": 0.125,
                "y": 0.09375
              }
            ],
            "resetTexCoords": [
              {
                "x": 0.15625,
                "y": 0.09375
              },
              {
                "x": 0.15625,
                "y": 0.0625
              },
              {
                "x": 0.125,
                "y": 0.0625
              },
              {
                "x": 0.125,
                "y": 0.09375
              }
            ],
            "filepath": "Assets/images/spritesheets/environment/tiles/blocks.png",
            "ID": 2619762,
            "isDirty": false
          },
          "name": "SpriteRenderer",
          "ID": 385185606,
          "isDirty": false
        }
      },
      {
        "type": "Burst.Engine.Source.Core.Physics.Components.Transform",
        "properties": {
          "position": {
            "x": -5.0,
            "y": -1.0
          },
          "scale": {
            "x": 1.0,
            "y": 1.0
          },
          "size": {
            "x": 1.0,
            "y": 1.0
          },
          "scaledSize": {
            "x": 1.0,
            "y": 1.0
          },
          "rotation": 0.0,
          "zIndex": 0,
          "name": "Transform",
          "ID": -683109387,
          "isDirty": false
        }
      }
    ],
    "serializedActor": true,
    "adjustSizeToTexture": false,
    "pickable": true
  },
  {
    "row": 13,
    "col": 0,
    "icon": {
      "width": 2048,
      "height": 2048,
      "filepath": "Assets/images/textures/icons/block.png",
      "ID": 1847234695,
      "isDirty": false
    },
    "name": "Block 22",
    "type": "Orion.blocks.Block",
    "ID": 22,
    "components": [
      {
        "type": "Burst.Engine.Source.Core.Render.SpriteRenderer",
        "properties": {
          "color": {
            "x": 1.0,
            "y": 1.0,
            "z": 1.0,
            "w": 1.0
          },
          "sprite": {
            "width": 16.0,
            "height": 16.0,
            "texCoords": [
              {
                "x": 0.15625,
                "y": 0.09375
              },
              {
                "x": 0.15625,
                "y": 0.0625
              },
              {
                "x": 0.125,
                "y": 0.0625
              },
              {
                "x": 0.125,
                "y": 0.09375
              }
            ],
            "resetTexCoords": [
              {
                "x": 0.15625,
                "y": 0.09375
              },
              {
                "x": 0.15625,
                "y": 0.0625
              },
              {
                "x": 0.125,
                "y": 0.0625
              },
              {
                "x": 0.125,
                "y": 0.09375
              }
            ],
            "filepath": "Assets/images/spritesheets/environment/tiles/blocks.png",
            "ID": 2619762,
            "isDirty": false
          },
          "name": "SpriteRenderer",
          "ID": 385185606,
          "isDirty": false
        }
      },
      {
        "type": "Burst.Engine.Source.Core.Physics.Components.Transform",
        "properties": {
          "position": {
            "x": -4.0,
            "y": -1.0
          },
          "scale": {
            "x": 1.0,
            "y": 1.0
          },
          "size": {
            "x": 1.0,
            "y": 1.0
          },
          "scaledSize": {
            "x": 1.0,
            "y": 1.0
          },
          "rotation": 0.0,
          "zIndex": 0,
          "name": "Transform",
          "ID": -683109387,
          "isDirty": false
        }
      }
    ],
    "serializedActor": true,
    "adjustSizeToTexture": false,
    "pickable": true
  },
  {
    "row": 13,
    "col": 0,
    "icon": {
      "width": 2048,
      "height": 2048,
      "filepath": "Assets/images/textures/icons/block.png",
      "ID": 1847234695,
      "isDirty": false
    },
    "name": "Block 23",
    "type": "Orion.blocks.Block",
    "ID": 23,
    "components": [
      {
        "type": "Burst.Engine.Source.Core.Render.SpriteRenderer",
        "properties": {
          "color": {
            "x": 1.0,
            "y": 1.0,
            "z": 1.0,
            "w": 1.0
          },
          "sprite": {
            "width": 16.0,
            "height": 16.0,
            "texCoords": [
              {
                "x": 0.15625,
                "y": 0.09375
              },
              {
                "x": 0.15625,
                "y": 0.0625
              },
              {
                "x": 0.125,
                "y": 0.0625
              },
              {
                "x": 0.125,
                "y": 0.09375
              }
            ],
            "resetTexCoords": [
              {
                "x": 0.15625,
                "y": 0.09375
              },
              {
                "x": 0.15625,
                "y": 0.0625
              },
              {
                "x": 0.125,
                "y": 0.0625
              },
              {
                "x": 0.125,
                "y": 0.09375
              }
            ],
            "filepath": "Assets/images/spritesheets/environment/tiles/blocks.png",
            "ID": 2619762,
            "isDirty": false
          },
          "name": "SpriteRenderer",
          "ID": 385185606,
          "isDirty": false
        }
      },
      {
        "type": "Burst.Engine.Source.Core.Physics.Components.Transform",
        "properties": {
          "position": {
            "x": -3.0,
            "y": -1.0
          },
          "scale": {
            "x": 1.0,
            "y": 1.0
          },
          "size": {
            "x": 1.0,
            "y": 1.0
          },
          "scaledSize": {
            "x": 1.0,
            "y": 1.0
          },
          "rotation": 0.0,
          "zIndex": 0,
          "name": "Transform",
          "ID": -683109387,
          "isDirty": false
        }
      }
    ],
    "serializedActor": true,
    "adjustSizeToTexture": false,
    "pickable": true
  },
  {
    "row": 13,
    "col": 0,
    "icon": {
      "width": 2048,
      "height": 2048,
      "filepath": "Assets/images/textures/icons/block.png",
      "ID": 1847234695,
      "isDirty": false
    },
    "name": "Block 24",
    "type": "Orion.blocks.Block",
    "ID": 24,
    "components": [
      {
        "type": "Burst.Engine.Source.Core.Render.SpriteRenderer",
        "properties": {
          "color": {
            "x": 1.0,
            "y": 1.0,
            "z": 1.0,
            "w": 1.0
          },
          "sprite": {
            "width": 16.0,
            "height": 16.0,
            "texCoords": [
              {
                "x": 0.15625,
                "y": 0.09375
              },
              {
                "x": 0.15625,
                "y": 0.0625
              },
              {
                "x": 0.125,
                "y": 0.0625
              },
              {
                "x": 0.125,
                "y": 0.09375
              }
            ],
            "resetTexCoords": [
              {
                "x": 0.15625,
                "y": 0.09375
              },
              {
                "x": 0.15625,
                "y": 0.0625
              },
              {
                "x": 0.125,
                "y": 0.0625
              },
              {
                "x": 0.125,
                "y": 0.09375
              }
            ],
            "filepath": "Assets/images/spritesheets/environment/tiles/blocks.png",
            "ID": 2619762,
            "isDirty": false
          },
          "name": "SpriteRenderer",
          "ID": 385185606,
          "isDirty": false
        }
      },
      {
        "type": "Burst.Engine.Source.Core.Physics.Components.Transform",
        "properties": {
          "position": {
            "x": -2.0,
            "y": -1.0
          },
          "scale": {
            "x": 1.0,
            "y": 1.0
          },
          "size": {
            "x": 1.0,
            "y": 1.0
          },
          "scaledSize": {
            "x": 1.0,
            "y": 1.0
          },
          "rotation": 0.0,
          "zIndex": 0,
          "name": "Transform",
          "ID": -683109387,
          "isDirty": false
        }
      }
    ],
    "serializedActor": true,
    "adjustSizeToTexture": false,
    "pickable": true
  },
  {
    "row": 13,
    "col": 0,
    "icon": {
      "width": 2048,
      "height": 2048,
      "filepath": "Assets/images/textures/icons/block.png",
      "ID": 1847234695,
      "isDirty": false
    },
    "name": "Block 25",
    "type": "Orion.blocks.Block",
    "ID": 25,
    "components": [
      {
        "type": "Burst.Engine.Source.Core.Render.SpriteRenderer",
        "properties": {
          "color": {
            "x": 1.0,
            "y": 1.0,
            "z": 1.0,
            "w": 1.0
          },
          "sprite": {
            "width": 16.0,
            "height": 16.0,
            "texCoords": [
              {
                "x": 0.15625,
                "y": 0.09375
              },
              {
                "x": 0.15625,
                "y": 0.0625
              },
              {
                "x": 0.125,
                "y": 0.0625
              },
              {
                "x": 0.125,
                "y": 0.09375
              }
            ],
            "resetTexCoords": [
              {
                "x": 0.15625,
                "y": 0.09375
              },
              {
                "x": 0.15625,
                "y": 0.0625
              },
              {
                "x": 0.125,
                "y": 0.0625
              },
              {
                "x": 0.125,
                "y": 0.09375
              }
            ],
            "filepath": "Assets/images/spritesheets/environment/tiles/blocks.png",
            "ID": 2619762,
            "isDirty": false
          },
          "name": "SpriteRenderer",
          "ID": 385185606,
          "isDirty": false
        }
      },
      {
        "type": "Burst.Engine.Source.Core.Physics.Components.Transform",
        "properties": {
          "position": {
            "x": -1.0,
            "y": -1.0
          },
          "scale": {
            "x": 1.0,
            "y": 1.0
          },
          "size": {
            "x": 1.0,
            "y": 1.0
          },
          "scaledSize": {
            "x": 1.0,
            "y": 1.0
          },
          "rotation": 0.0,
          "zIndex": 0,
          "name": "Transform",
          "ID": -683109387,
          "isDirty": false
        }
      }
    ],
    "serializedActor": true,
    "adjustSizeToTexture": false,
    "pickable": true
  }
]